myssml/MySSML.py
myssml/MySSML_1.1.14.py
myssml/MySSML_1.1.8.py
myssml/__init__.py
myssml-1.1.16.dist-info/LICENSE
myssml-1.1.16.dist-info/METADATA
myssml-1.1.16.dist-info/WHEEL
myssml-1.1.16.dist-info/top_level.txt
myssml-1.1.16.dist-info/RECORD
